[
  {
    "date": "2025-05-02",
    "head_line": "绿鹭",
    "title": "维多利亚睡莲上的绿鹭，潘塔纳尔 ，巴西",
    "copyright": "© Gerald Corsi/Getty Images",
    "desc": "在巴西郁郁葱葱的潘塔纳尔湿地，一只绿鹭栖息在一片维多利亚王莲的叶面上。这种水鸟，也被称为红树鹭，约16英寸高，是耐心的猎手，擅长埋伏猎物。它会采用聪明的策略，例如投下羽毛或昆虫引诱鱼类上钩。绿鹭常见于南美洲的湿地，也分布于北美、澳大利亚、非洲、亚洲、新几内亚和太平洋岛屿。",
    "image_url": "https://www.bing.com/th?id=OHR.BrazilHeron_ZH-CN7200229300_UHD.jpg",
    "preview_url": "https://www.bing.com/th?id=OHR.BrazilHeron_ZH-CN7200229300_400x240.jpg",
    "main_text": "绿鹭有时会使用诱饵，它会小心地将一根羽毛或一片树叶投放到水面上，等候前来探查的鱼类。",
    "sizes": {
      "UHD": "https://www.bing.com/th?id=OHR.BrazilHeron_ZH-CN7200229300_UHD.jpg",
      "1920x1200": "https://www.bing.com/th?id=OHR.BrazilHeron_ZH-CN7200229300_1920x1200.jpg",
      "1920x1080": "https://www.bing.com/th?id=OHR.BrazilHeron_ZH-CN7200229300_1920x1080.jpg",
      "1080x1920": "https://www.bing.com/th?id=OHR.BrazilHeron_ZH-CN7200229300_1080x1920.jpg",
      "1366x768": "https://www.bing.com/th?id=OHR.BrazilHeron_ZH-CN7200229300_1366x768.jpg",
      "1280x768": "https://www.bing.com/th?id=OHR.BrazilHeron_ZH-CN7200229300_1280x768.jpg",
      "1024x768": "https://www.bing.com/th?id=OHR.BrazilHeron_ZH-CN7200229300_1024x768.jpg",
      "800x600": "https://www.bing.com/th?id=OHR.BrazilHeron_ZH-CN7200229300_800x600.jpg",
      "800x480": "https://www.bing.com/th?id=OHR.BrazilHeron_ZH-CN7200229300_800x480.jpg",
      "768x1280": "https://www.bing.com/th?id=OHR.BrazilHeron_ZH-CN7200229300_768x1280.jpg",
      "720x1280": "https://www.bing.com/th?id=OHR.BrazilHeron_ZH-CN7200229300_720x1280.jpg",
      "640x480": "https://www.bing.com/th?id=OHR.BrazilHeron_ZH-CN7200229300_640x480.jpg",
      "480x800": "https://www.bing.com/th?id=OHR.BrazilHeron_ZH-CN7200229300_480x800.jpg",
      "400x240": "https://www.bing.com/th?id=OHR.BrazilHeron_ZH-CN7200229300_400x240.jpg",
      "320x240": "https://www.bing.com/th?id=OHR.BrazilHeron_ZH-CN7200229300_320x240.jpg",
      "240x320": "https://www.bing.com/th?id=OHR.BrazilHeron_ZH-CN7200229300_240x320.jpg"
    }
  },
  {
    "date": "2025-05-01",
    "head_line": "芬芳的传统",
    "title": "鸡蛋花，夏威夷，美国",
    "copyright": "© Miranda Jans/Getty Images",
    "desc": "方式纪念这一天，让整个群岛沐浴在花香之中。每年5月1日，夏威夷庆祝“花环节”，这一传统节日旨在弘扬文化、手工技艺，以及无处不在的阿罗哈精神，这种精神被描述为“每个人内心中思想与情感的协调统一”。 自1928年起，这一传统就在夏威夷广为流行。花环：由花朵、叶子或贝壳编织而成的花冠，成为人与人之间联结的象征。节日的灵感来自诗人唐·布兰丁，他提出设立一个专属于夏威夷的标志性花环节日。当地作家格蕾丝·塔沃·沃伦为其赋予口号：“五一劳动节就是夏威夷的花环节”，这一传统由此迅速生根发芽。",
    "image_url": "https://www.bing.com/th?id=OHR.PinkPlumeria_ZH-CN3890147555_UHD.jpg",
    "preview_url": "https://www.bing.com/th?id=OHR.PinkPlumeria_ZH-CN3890147555_400x240.jpg",
    "main_text": "花环在夏威夷文化中意义非凡，它象征着难以言说的“阿罗哈”情感。“阿罗哈”一词的含义会随着场合而变化，它既可以代表告别、问候、爱、希望，也可以表达喜悦。",
    "sizes": {
      "UHD": "https://www.bing.com/th?id=OHR.PinkPlumeria_ZH-CN3890147555_UHD.jpg",
      "1920x1200": "https://www.bing.com/th?id=OHR.PinkPlumeria_ZH-CN3890147555_1920x1200.jpg",
      "1920x1080": "https://www.bing.com/th?id=OHR.PinkPlumeria_ZH-CN3890147555_1920x1080.jpg",
      "1080x1920": "https://www.bing.com/th?id=OHR.PinkPlumeria_ZH-CN3890147555_1080x1920.jpg",
      "1366x768": "https://www.bing.com/th?id=OHR.PinkPlumeria_ZH-CN3890147555_1366x768.jpg",
      "1280x768": "https://www.bing.com/th?id=OHR.PinkPlumeria_ZH-CN3890147555_1280x768.jpg",
      "1024x768": "https://www.bing.com/th?id=OHR.PinkPlumeria_ZH-CN3890147555_1024x768.jpg",
      "800x600": "https://www.bing.com/th?id=OHR.PinkPlumeria_ZH-CN3890147555_800x600.jpg",
      "800x480": "https://www.bing.com/th?id=OHR.PinkPlumeria_ZH-CN3890147555_800x480.jpg",
      "768x1280": "https://www.bing.com/th?id=OHR.PinkPlumeria_ZH-CN3890147555_768x1280.jpg",
      "720x1280": "https://www.bing.com/th?id=OHR.PinkPlumeria_ZH-CN3890147555_720x1280.jpg",
      "640x480": "https://www.bing.com/th?id=OHR.PinkPlumeria_ZH-CN3890147555_640x480.jpg",
      "480x800": "https://www.bing.com/th?id=OHR.PinkPlumeria_ZH-CN3890147555_480x800.jpg",
      "400x240": "https://www.bing.com/th?id=OHR.PinkPlumeria_ZH-CN3890147555_400x240.jpg",
      "320x240": "https://www.bing.com/th?id=OHR.PinkPlumeria_ZH-CN3890147555_320x240.jpg",
      "240x320": "https://www.bing.com/th?id=OHR.PinkPlumeria_ZH-CN3890147555_240x320.jpg"
    }
  }
]